spectronator/__init__.py
spectronator/spectronator.py
spectronator/tkgui.py
spectronator/version.py
spectronator-0.0.2.dist-info/LICENSE
spectronator-0.0.2.dist-info/METADATA
spectronator-0.0.2.dist-info/WHEEL
spectronator-0.0.2.dist-info/top_level.txt
spectronator-0.0.2.dist-info/RECORD
