Metadata-Version: 2.1
Name: spectronator
Version: 0.0.2
Summary: A spectral sensitivity analyser for time series data
Author-email: Joni Kemppainen <joni.kemppainen@windowslive.com>
Project-URL: Homepage, https://github.com/jkemppainen/spectronator
Project-URL: Issues, https://github.com/jkemppainen/spectronator/issues
Classifier: Programming Language :: Python :: 3
Classifier: License :: OSI Approved :: GNU General Public License v3 (GPLv3)
Classifier: Operating System :: OS Independent
Requires-Python: >=3.6
License-File: LICENSE
Requires-Dist: scipy
Requires-Dist: matplotlib
Requires-Dist: tk-steroids
Requires-Dist: python-biosystfiles
